INSTALL.rst
LICENSE
LVdata.csv
LVinput.csv
MANIFEST.in
README.rst
example1.py
example2.py
example3.py
example4.py
example5.py
setup.cfg
setup.py
testcsv.csv
testpackage.py
testsas.sas7bdat
EasyModeler.egg-info/PKG-INFO
EasyModeler.egg-info/SOURCES.txt
EasyModeler.egg-info/dependency_links.txt
EasyModeler.egg-info/not-zip-safe
EasyModeler.egg-info/top_level.txt
emlib/__init__.py
emlib/emlib.py