Metadata-Version: 1.1
Name: EasyModeler
Version: 2.2.3
Summary: Simple ODE Tools for Modelers
Home-page: https://pypi.python.org/pypi/EasyModeler
Author: Evan L Turner
Author-email: evanlee.turner@gmail.com
License: BSD
Keywords: EasyModel,GCOOS,ODE,SciPy,ODEINT,calibration
Platform: UNKNOWN
Classifier: Development Status :: 4 - Beta
Classifier: Environment :: Console
Classifier: Intended Audience :: Science/Research
Classifier: Operating System :: OS Independent
Classifier: Programming Language :: Python
Classifier: Topic :: Scientific/Engineering
Classifier: Topic :: Scientific/Engineering :: Mathematics
Classifier: Topic :: Scientific/Engineering :: Visualization
Classifier: Topic :: Utilities
Requires: SciPy
Requires: NumPy
Requires: matplotlib
